peachiia/__init__.py
peachiia/main.py
test2/__init__.py
test2/main.py
test2/tt.py
utils/__init__.py
utils/dummy.py
peachiia-0.0.1.dist-info/METADATA
peachiia-0.0.1.dist-info/WHEEL
peachiia-0.0.1.dist-info/top_level.txt
peachiia-0.0.1.dist-info/RECORD
