Metadata-Version: 2.1
Name: peachiia
Version: 0.0.1
Summary: Mostly useless modules sewn together, with a few sparks of potential, by Peachiia.
Author: Peachiia
Author-email: mail@peachiia.com
Classifier: Programming Language :: Python :: 3
Classifier: License :: OSI Approved :: MIT License
Classifier: Operating System :: OS Independent
Requires-Python: >=3.6
